pyscf/soscf/m3soscf.py
pyscf/soscf/sigma_utils.py
pyscf/soscf/test/test_m3soscf.py
pyscf/msdft/__init__.py
pyscf/msdft/noci.py
pyscf/msdft/tests/test_noci.py
pyscf/mcpdft/pdft_eff.py
pyscf/mcpdft/_libxc.py
pyscf/mcpdft/tfnal_derivs.py
pyscf/mcpdft/__init__.py
pyscf/mcpdft/pdft_feff.py
pyscf/mcpdft/chkfile.py
pyscf/mcpdft/otfnal.py
pyscf/mcpdft/_dms.py
pyscf/mcpdft/pdft_veff.py
pyscf/mcpdft/xmspdft.py
pyscf/mcpdft/mspdft.py
pyscf/mcpdft/otpd.py
pyscf/mcpdft/cmspdft.py
pyscf/mcpdft/mcpdft.py
pyscf/mcpdft/lpdft.py
pyscf/mcpdft/test/test_cmspdft.py
pyscf/mcpdft/test/test_spingaps_atoms.py
pyscf/mcpdft/test/test_mspdft.py
pyscf/mcpdft/test/test_lpdft.py
pyscf/mcpdft/test/test_otfnal.py
pyscf/mcpdft/test/test_otpd.py
pyscf/mcpdft/test/test_mcpdft.py
pyscf/mcpdft/test/test_diatomic_energies.py
pyscf/mcpdft/test/test_pdft_feff.py
pyscf/mcpdft/test/test_xmspdft.py
pyscf/mcpdft/test/test_pdft_veff.py
pyscf/mcpdft/test/test_mgga.py
pyscf/lrdf/__init__.py
pyscf/lrdf/lrdf.py
pyscf/lrdf/hessian/rhf.py
pyscf/lrdf/hessian/__init__.py
pyscf/lrdf/test/test_lrdf.py
pyscf/lrdf/test/test_df_hess.py
pyscf/lrdf/test/test_df_grad.py
pyscf/lrdf/grad/rhf.py
pyscf/lrdf/grad/__init__.py
pyscf/mcdcft/__init__.py
pyscf/mcdcft/mcdcft.py
pyscf/mcdcft/dcfnal.py
pyscf/mcdcft/test/test_energy_h2.py
pyscf/pbc/scf/khf_stagger.py
pyscf/pbc/scf/test/test_khf_stagger.py
pyscf/lib/libpdft.so
pyscf/lib/CMakeLists.txt
pyscf/lib/libxc_itrf2.so
pyscf/lib/dft/libxc_itrf2.c
pyscf/pprpa/rpprpa_davidson.py
pyscf/pprpa/__init__.py
pyscf/pprpa/rpprpa_direct.py
pyscf/pprpa/upprpa_direct.py
pyscf/pprpa/tests/test_rpprpa.py
pyscf/sftda/scf_genrep_sftd.py
pyscf/sftda/__init__.py
pyscf/sftda/numint_sftd.py
pyscf/sftda/uks_sf.py
pyscf/sftda/tools_td.py
pyscf/sftda/numint2c_sftd.py
pyscf/sftda/uhf_sf.py
pyscf/sftda/test/test_uks_sf_tda.py
pyscf/tools/trexio.py
pyscf/tools/test/test_trexio.py
pyscf/df/grad/mspdft.py
pyscf/df/grad/mcpdft.py
pyscf_forge-1.0.3.dist-info/METADATA
pyscf_forge-1.0.3.dist-info/RECORD
pyscf_forge-1.0.3.dist-info/top_level.txt
pyscf_forge-1.0.3.dist-info/NOTICE
pyscf_forge-1.0.3.dist-info/WHEEL
pyscf_forge-1.0.3.dist-info/LICENSE
