Metadata-Version: 2.2
Name: pyscf_forge
Version: 1.0.3
Summary: Staging ground for PySCF core features
Author: Pyscf Developer
License-File: LICENSE
License-File: NOTICE
Requires-Dist: pyscf
Requires-Dist: numpy
Dynamic: author
Dynamic: description
Dynamic: description-content-type
Dynamic: requires-dist
Dynamic: summary
